<!--
/**
* +- - - - - - - - - - - - - - - - - - - - - - - - - - - - - - - - - - +
* | This MySource Matrix CMS file is Copyright (c) Squiz Pty Ltd       |
* | ACN 084 670 600                                                    |
* +- - - - - - - - - - - - - - - - - - - - - - - - - - - - - - - - - - +
* | IMPORTANT: Your use of this Software is subject to the terms of    |
* | the Licence provided in the file licence.txt. If you cannot find   |
* | this file please contact Squiz (www.squiz.net) so we may provide   |
* | you a copy.                                                        |
* +- - - - - - - - - - - - - - - - - - - - - - - - - - - - - - - - - - +
*
* $Id: lang_strings.xml,v 1.1 2012/01/19 01:33:05 cupreti Exp $
*
*/
-->

<strings>
<string source="page_events_search_filter_select_options">Select filter type</string>
<string source="page_events_search_filter_select_options_single_date">Single Date</string>
<string source="page_events_search_filter_select_options_date_range">Date Range</string>
<string source="page_events_search_filter_select_options_fuzzy_dropdown">Fuzzy Date (Dropdown selection)</string>
<string source="page_events_search_filter_select_options_fuzzy_checkboxes">Fuzzy Date (Checkboxes selection)</string>
<string source="page_events_search_filter_field">Input field for Calendar Event filter %s</string>
</strings>
