<!--
/**
* +- - - - - - - - - - - - - - - - - - - - - - - - - - - - - - - - - - +
* | This MySource Matrix CMS file is Copyright (c) Squiz Pty Ltd       |
* | ACN 084 670 600                                                    |
* +- - - - - - - - - - - - - - - - - - - - - - - - - - - - - - - - - - +
* | IMPORTANT: Your use of this Software is subject to the terms of    |
* | the Licence provided in the file licence.txt. If you cannot find   |
* | this file please contact Squiz (www.squiz.net) so we may provide   |
* | you a copy.                                                        |
* +- - - - - - - - - - - - - - - - - - - - - - - - - - - - - - - - - - +
*
* $Id: tables.xml,v 1.6 2008/11/24 23:17:12 mbrydon Exp $
*
*/
-->

<schema>
	<tables>
		<table name="cal_date_val" require_rollback="1">
			<columns>
				<column name="assetid" allow_null="0">
					<type>VARCHAR(15)</type>
					<type_variations />
					<default />
					<description />
				</column>
				<column name="frequency" allow_null="1">
					<type>CHAR(3)</type>
					<type_variations />
					<default />
					<description />
				</column>
				<column name="period" allow_null="0">
					<type>SMALLINT</type>
					<type_variations />
					<default>1</default>
					<description />
				</column>
				<column name="start_date_seconds" allow_null="1">
					<type>SMALLINT</type>
					<type_variations />
					<default />
					<description />
				</column>
				<column name="start_date_minutes" allow_null="1">
					<type>SMALLINT</type>
					<type_variations />
					<default />
					<description />
				</column>
				<column name="start_date_hours" allow_null="1">
					<type>SMALLINT</type>
					<type_variations />
					<default />
					<description />
				</column>
				<column name="start_date_mday" allow_null="1">
					<type>SMALLINT</type>
					<type_variations />
					<default />
					<description />
				</column>
				<column name="start_date_rmday" allow_null="1">
					<type>SMALLINT</type>
					<type_variations />
					<default />
					<description />
				</column>
				<column name="start_date_wday" allow_null="1">
					<type>SMALLINT</type>
					<type_variations />
					<default />
					<description />
				</column>
				<column name="start_date_wdom" allow_null="1">
					<type>SMALLINT</type>
					<type_variations />
					<default />
					<description />
				</column>
				<column name="start_date_rwdom" allow_null="1">
					<type>SMALLINT</type>
					<type_variations />
					<default />
					<description />
				</column>
				<column name="start_date_mon" allow_null="1">
					<type>SMALLINT</type>
					<type_variations />
					<default />
					<description />
				</column>
				<column name="start_date_year" allow_null="1">
					<type>SMALLINT</type>
					<type_variations />
					<default />
					<description />
				</column>
				<column name="start_date_yday" allow_null="1">
					<type>SMALLINT</type>
					<type_variations />
					<default />
					<description />
				</column>
				<column name="start_date_ryday" allow_null="1">
					<type>SMALLINT</type>
					<type_variations />
					<default />
					<description />
				</column>
				<column name="start_date_ts" allow_null="1">
					<type>INT</type>
					<type_variations />
					<default />
					<description />
				</column>
				<column name="start_date_ds" allow_null="1">
					<type>INT</type>
					<type_variations />
					<default />
					<description />
				</column>
				<column name="start_date_ms" allow_null="1">
					<type>INT</type>
					<type_variations />
					<default />
					<description />
				</column>
				<column name="end_date_seconds" allow_null="1">
					<type>SMALLINT</type>
					<type_variations />
					<default />
					<description />
				</column>
				<column name="end_date_minutes" allow_null="1">
					<type>SMALLINT</type>
					<type_variations />
					<default />
					<description />
				</column>
				<column name="end_date_hours" allow_null="1">
					<type>SMALLINT</type>
					<type_variations />
					<default />
					<description />
				</column>
				<column name="end_date_mday" allow_null="1">
					<type>SMALLINT</type>
					<type_variations />
					<default />
					<description />
				</column>
				<column name="end_date_rmday" allow_null="1">
					<type>SMALLINT</type>
					<type_variations />
					<default />
					<description />
				</column>
				<column name="end_date_wday" allow_null="1">
					<type>SMALLINT</type>
					<type_variations />
					<default />
					<description />
				</column>
				<column name="end_date_wdom" allow_null="1">
					<type>SMALLINT</type>
					<type_variations />
					<default />
					<description />
				</column>
				<column name="end_date_rwdom" allow_null="1">
					<type>SMALLINT</type>
					<type_variations />
					<default />
					<description />
				</column>
				<column name="end_date_mon" allow_null="1">
					<type>SMALLINT</type>
					<type_variations />
					<default />
					<description />
				</column>
				<column name="end_date_year" allow_null="1">
					<type>SMALLINT</type>
					<type_variations />
					<default />
					<description />
				</column>
				<column name="end_date_yday" allow_null="1">
					<type>SMALLINT</type>
					<type_variations />
					<default />
					<description />
				</column>
				<column name="end_date_ryday" allow_null="1">
					<type>SMALLINT</type>
					<type_variations />
					<default />
					<description />
				</column>
				<column name="end_date_ts" allow_null="1">
					<type>INT</type>
					<type_variations />
					<default />
					<description />
				</column>
				<column name="end_date_ds" allow_null="1">
					<type>INT</type>
					<type_variations />
					<default />
					<description />
				</column>
				<column name="end_date_ms" allow_null="1">
					<type>INT</type>
					<type_variations />
					<default />
					<description />
				</column>
				<column name="stop_date" allow_null="0">
					<type>CHAR(10)</type>
					<type_variations />
					<default>'----------'</default>
					<description />
				</column>
			</columns>
			<keys>
				<primary_key>
					<column name="assetid" />
				</primary_key>
			</keys>
			<indexes />
		</table>
	</tables>
	<sequences />
</schema>