<?xml version='1.0' encoding='UTF-8' ?>
<?xml-stylesheet href="../../../../packages/asset.xsl" type="text/xsl"?>

<!--
/**
* +- - - - - - - - - - - - - - - - - - - - - - - - - - - - - - - - - - +
* | This MySource Matrix CMS file is Copyright (c) Squiz Pty Ltd       |
* | ACN 084 670 600                                                    |
* +- - - - - - - - - - - - - - - - - - - - - - - - - - - - - - - - - - +
* | IMPORTANT: Your use of this Software is subject to the terms of    |
* | the Licence provided in the file licence.txt. If you cannot find   |
* | this file please contact Squiz (www.squiz.net) so we may provide   |
* | you a copy.                                                        |
* +- - - - - - - - - - - - - - - - - - - - - - - - - - - - - - - - - - +
*
* $Id: asset.xml,v 1.1 2007/05/31 04:53:34 rong Exp $
*
*/
-->

<asset_info xmlns:xsi="http://www.w3.org/2001/XMLSchema-instance">
	<package>__core__</package>
	<type_code>cron_job_clear_matrix_cache</type_code>
	<version>0.1</version>
	<name>Clear Matrix Cache Scheduled Job</name>
	<description>Allows the scheduling of a clear Matrix cache scheduled job to be done by the system at a point in time.</description>
	<instantiable>no</instantiable>
	<allowed_access>system</allowed_access>
	<parent_type>cron_job</parent_type>
	<requirements />
	<flash_menu_path />
</asset_info>
