<!--
/**
* +- - - - - - - - - - - - - - - - - - - - - - - - - - - - - - - - - - +
* | This MySource Matrix Module file is Copyright (c) Squiz Pty Ltd    |
* | ACN 084 670 600                                                    |
* +- - - - - - - - - - - - - - - - - - - - - - - - - - - - - - - - - - +
* | IMPORTANT: This Module is not available under an open source       |
* | license and consequently distribution of this and any other files  |
* | that comprise this Module is prohibited. You may only use this     |
* | Module if you have the written consent of Squiz.                   |
* +- - - - - - - - - - - - - - - - - - - - - - - - - - - - - - - - - - +
*
* $Id: lang_strings.xml,v 1.2.8.1 2008/04/22 00:23:24 bshkara Exp $
*
*
* Ecommerce Package Localised Strings File
*/
-->

<strings>
	<string source="ecom_product_price_note_value">Zero = Free &lt;br/&gt; Blank = Value Not Known</string>
	<string source="ecom_product_price_value_has_tax">Product Price Already Includes Tax</string>
	<string source="ecom_product_price_note_value_has_tax">Select this if the the above price value already includes the tax for this product.</string>
	<string source="ecom_product_price_calculate_tax">Calculate Tax During Checkout</string>
	<string source="ecom_product_price_note_calculate_tax">If selected, tax will be calculated and be displayed during the checkout process.</string>
</strings>
